niatlas/__init__.py
niatlas/niatlas.py
niatlas-0.0.1.dist-info/LICENSE
niatlas-0.0.1.dist-info/METADATA
niatlas-0.0.1.dist-info/WHEEL
niatlas-0.0.1.dist-info/top_level.txt
niatlas-0.0.1.dist-info/RECORD
